Metadata-Version: 2.1
Name: alpdataneuron
Version: 0.2.10
Summary: alpdataneuron package
Home-page: http://20.43.152.82
Author: Nishant Chhetri
Author-email: nishant.chhetri@precily.com
License: UNKNOWN
Platform: UNKNOWN
Classifier: Programming Language :: Python :: 3
Classifier: License :: OSI Approved :: MIT License
Classifier: Operating System :: OS Independent
Requires-Python: >=3.6
